LICENSE.txt
MANIFEST.in
README.rst
setup.cfg
setup.py
connect_sdk_python3.egg-info/PKG-INFO
connect_sdk_python3.egg-info/SOURCES.txt
connect_sdk_python3.egg-info/dependency_links.txt
connect_sdk_python3.egg-info/requires.txt
connect_sdk_python3.egg-info/top_level.txt
worldline/__init__.py
worldline/connect/__init__.py
worldline/connect/sdk/__init__.py
worldline/connect/sdk/api_resource.py
worldline/connect/sdk/call_context.py
worldline/connect/sdk/client.py
worldline/connect/sdk/communicator.py
worldline/connect/sdk/communicator_configuration.py
worldline/connect/sdk/factory.py
worldline/connect/sdk/proxy_configuration.py
worldline/connect/sdk/authentication/__init__.py
worldline/connect/sdk/authentication/authenticator.py
worldline/connect/sdk/authentication/authorization_type.py
worldline/connect/sdk/authentication/v1hmac_authenticator.py
worldline/connect/sdk/communication/__init__.py
worldline/connect/sdk/communication/communication_exception.py
worldline/connect/sdk/communication/connection.py
worldline/connect/sdk/communication/default_connection.py
worldline/connect/sdk/communication/metadata_provider.py
worldline/connect/sdk/communication/multipart_form_data_object.py
worldline/connect/sdk/communication/multipart_form_data_request.py
worldline/connect/sdk/communication/not_found_exception.py
worldline/connect/sdk/communication/param_request.py
worldline/connect/sdk/communication/pooled_connection.py
worldline/connect/sdk/communication/request_header.py
worldline/connect/sdk/communication/request_param.py
worldline/connect/sdk/communication/response_exception.py
worldline/connect/sdk/communication/response_header.py
worldline/connect/sdk/domain/__init__.py
worldline/connect/sdk/domain/data_object.py
worldline/connect/sdk/domain/shopping_cart_extension.py
worldline/connect/sdk/domain/uploadable_file.py
worldline/connect/sdk/json/__init__.py
worldline/connect/sdk/json/default_marshaller.py
worldline/connect/sdk/json/marshaller.py
worldline/connect/sdk/json/marshaller_syntax_exception.py
worldline/connect/sdk/log/__init__.py
worldline/connect/sdk/log/body_obfuscator.py
worldline/connect/sdk/log/communicator_logger.py
worldline/connect/sdk/log/header_obfuscator.py
